simplepro/__init__.py
simplepro/action.py
simplepro/admin.py
simplepro/apps.py
simplepro/conf.py
simplepro/core.py
simplepro/decorators.py
simplepro/dialog.py
simplepro/filters.py
simplepro/forms.py
simplepro/handlers.py
simplepro/middlewares.py
simplepro/models.py
simplepro/urls.py
simplepro/utils.py
simplepro/bawa/views.py
simplepro/components/__init__.py
simplepro/components/utils.py
simplepro/components/fields/__init__.py
simplepro/components/fields/char_field.py
simplepro/components/fields/input_number_field.py
simplepro/components/fields/input_password_field.py
simplepro/components/fields/radio_field.py
simplepro/components/widgets/__init__.py
simplepro/components/widgets/input.py
simplepro/components/widgets/input_char.py
simplepro/components/widgets/input_number.py
simplepro/components/widgets/input_password.py
simplepro/editor/__init__.py
simplepro/editor/utils.py
simplepro/editor/views.py
simplepro/editor/fields/__init__.py
simplepro/editor/fields/json_text_field.py
simplepro/editor/widgets/__init__.py
simplepro/editor/widgets/json_editor_widget.py
simplepro/editor/widgets/md_editor_widget.py
simplepro/editor/widgets/u_editor_widget.py
simplepro/group/utils.py
simplepro/group/view.py
simplepro/lib/pkHelper.py
simplepro/locale/zh_Hans/LC_MESSAGES/django.mo
simplepro/locale/zh_Hans/LC_MESSAGES/django.po
simplepro/locale/zh_Hans/LC_MESSAGES/make.sh
simplepro/management/commands/active.py
simplepro/management/commands/migrate_menu.py
simplepro/monitor/test.py
simplepro/monitor/utils.py
simplepro/monitor/views.py
simplepro/static/admin/bawa/BawaData.json
simplepro/static/admin/bawa/demo.html
simplepro/static/admin/bawa/index.html
simplepro/static/admin/bawa/render.common.js
simplepro/static/admin/bawa/render.umd.js
simplepro/static/admin/bawa/render.umd.min.js
simplepro/static/admin/bawa/charts/bar/basic.json
simplepro/static/admin/bawa/charts/bubble/smoking-rate.json
simplepro/static/admin/bawa/charts/bullet/basic.json
DjangoAsyncAdmin-6.13.0.dist-info/LICENSE
DjangoAsyncAdmin-6.13.0.dist-info/METADATA
DjangoAsyncAdmin-6.13.0.dist-info/WHEEL
DjangoAsyncAdmin-6.13.0.dist-info/top_level.txt
DjangoAsyncAdmin-6.13.0.dist-info/RECORD
