Metadata-Version: 2.1
Name: DjangoAsyncAdmin
Version: 6.13.0
Summary: A second development project based on SimplePro for out of print version 6.5.2
Author-email: Sadam·Sadik <1903249375@qq.com>
Project-URL: Homepage, https://haoke98.github.io/DjangoAsyncAdmin/
Project-URL: Bug Tracker, https://github.com/Haoke98/DjangoAsyncAdmin/issues
Project-URL: Documentation, https://haoke98.github.io/DjangoAsyncAdmin/
Project-URL: Components Docs, https://haoke98.github.io/DjangoAsyncAdmin/components.html
Project-URL: Demo, https://github.com/Haoke98/AllKeeper
Classifier: Programming Language :: Python :: 3
Classifier: License :: OSI Approved :: Apache Software License
Classifier: Operating System :: OS Independent
Requires-Python: >=3.6
License-File: LICENSE
Requires-Dist: django >=2.1
Requires-Dist: django-simpleui >=2024.8.28
Requires-Dist: django-import-export
Requires-Dist: requests
Requires-Dist: rsa
Requires-Dist: psutil >=5.9.8
